{
  "build_from": {
    "amd64": "homeassistant/amd64-base:3.11",
    "i386": "homeassistant/i386-base:3.11",
    "armhf": "homeassistant/armhf-base:3.11",
    "armv7": "homeassistant/armv7-base:3.11",
    "aarch64": "homeassistant/aarch64-base:3.11"
  },
  "args": {
    "OZW_VERSION": "a35732f107e3620578c1cb9f027e0a71b5410697",
    "QTOZW_VERSION": "337e48807568e4e7f90d3b8441cc126c9e057cde",
    "QTOZWADMIN_VERSION": "278427be5d52a04aaab8e9d767f7e9a210bc1b58",
    "QTMQTT_VERSION": "5.12.8",
    "QTWEBSOCKETS_VERSION": "5.12.8"
  }
}
